z0scan/LICENSE
z0scan/README.MD
z0scan/README.zh-CN.MD
z0scan/__init__.py
z0scan/config.py
z0scan/requirements.txt
z0scan/reverse.py
z0scan/setup.py
z0scan/z0.py
z0scan/api/__init__.py
z0scan/certs/ca.crt
z0scan/certs/ca.pem
z0scan/data/__init__.py
z0scan/data/report.template
z0scan/data/z0scan.db
z0scan/data/dict/__init__.py
z0scan/data/dict/agents.txt
z0scan/data/dict/backdoor.txt
z0scan/data/dict/backup.txt
z0scan/data/dict/log.txt
z0scan/data/dict/origins.txt
z0scan/data/dict/password.txt
z0scan/data/dict/phpinfo.txt
z0scan/data/dict/sqli-password.txt
z0scan/data/dict/username.txt
z0scan/data/rule/__init__.py
z0scan/data/rule/cms_loginpage.py
z0scan/data/rule/js_sensi.py
z0scan/data/rule/phpinfo_sensi.py
z0scan/data/rule/sqli_error.py
z0scan/data/rule/wafsignatures.py
z0scan/doc/CHANGELOG.MD
z0scan/doc/DEV.MD
z0scan/fingprints/__init__.py
z0scan/fingprints/os/__init__.py
z0scan/fingprints/os/darwin.py
z0scan/fingprints/os/linux.py
z0scan/fingprints/os/windows.py
z0scan/fingprints/programing/__init__.py
z0scan/fingprints/programing/asp.py
z0scan/fingprints/programing/java.py
z0scan/fingprints/programing/php.py
z0scan/fingprints/webserver/__init__.py
z0scan/fingprints/webserver/apache-tomcat.py
z0scan/fingprints/webserver/apache.py
z0scan/fingprints/webserver/iis.py
z0scan/fingprints/webserver/nginx.py
z0scan/fingprints/webserver/oss.py
z0scan/fingprints/webserver/tengine.py
z0scan/lib/__init__.py
z0scan/lib/api/__init__.py
z0scan/lib/api/dnslog.py
z0scan/lib/api/reverse_api.py
z0scan/lib/controller/__init__.py
z0scan/lib/controller/controller.py
z0scan/lib/core/__init__.py
z0scan/lib/core/common.py
z0scan/lib/core/data.py
z0scan/lib/core/datatype.py
z0scan/lib/core/db.py
z0scan/lib/core/enums.py
z0scan/lib/core/exection.py
z0scan/lib/core/loader.py
z0scan/lib/core/log.py
z0scan/lib/core/option.py
z0scan/lib/core/output.py
z0scan/lib/core/plugins.py
z0scan/lib/core/settings.py
z0scan/lib/core/spiderset.py
z0scan/lib/core/wafDetector.py
z0scan-2035.6.9.0.dist-info/METADATA
z0scan-2035.6.9.0.dist-info/WHEEL
z0scan-2035.6.9.0.dist-info/entry_points.txt
z0scan-2035.6.9.0.dist-info/top_level.txt
z0scan-2035.6.9.0.dist-info/RECORD
