Metadata-Version: 2.2
Name: z0scan
Version: 2035.6.9.0
Summary: An auxiliary active and passive scanning tool with Web and Full-Version Service vulnerability detection as the core. | 一款以Web与全版本服务漏洞检测为核心的辅助性主、被动扫描工具.
Home-page: https://github.com/JiuZero/z0scan
Author: JiuZero
Author-email: jiuzer0@qq.com
Keywords: z0scan,security,scanner,web,python3
Platform: any
Classifier: Topic :: Security
Classifier: Programming Language :: Python :: 3
Classifier: License :: OSI Approved :: GNU General Public License v2 (GPLv2)
Requires-Python: >=3.0
Requires-Dist: asn1crypto>=0.24.0
Requires-Dist: certifi>=2019.6.16
Requires-Dist: cffi>=1.15.0
Requires-Dist: chardet>=3.0.4
Requires-Dist: colorama
Requires-Dist: cryptography>=37.0.2
Requires-Dist: cssselect>=1.1.0
Requires-Dist: idna>=2.8
Requires-Dist: lxml>=4.9.0
Requires-Dist: pycparser>=2.19
Requires-Dist: pyjsparser>=2.7.1
Requires-Dist: pyOpenSSL>=18.0.0
Requires-Dist: PySocks>=1.7.1
Requires-Dist: requests>=2.28.0
Requires-Dist: requests-toolbelt>=0.9.1
Requires-Dist: six>=1.12.0
Requires-Dist: tld>=0.9.3
Requires-Dist: urllib3>=1.26.5
Requires-Dist: future
Requires-Dist: bs4
Requires-Dist: dnspython
Requires-Dist: fake_useragent>=2.2.0
Requires-Dist: tldextract
Requires-Dist: viewstate
Dynamic: author
Dynamic: author-email
Dynamic: classifier
Dynamic: description
Dynamic: description-content-type
Dynamic: home-page
Dynamic: keywords
Dynamic: platform
Dynamic: requires-dist
Dynamic: requires-python
Dynamic: summary
